predictrampyfinance/__init__.py
predictrampyfinance/api.py
predictrampyfinance/symbol.js
predictrampyfinance/stock_json/20MICRONS.json
predictrampyfinance/stock_json/21STCENMGM.json
predictrampyfinance/stock_json/3IINFOLTD.json
predictrampyfinance/stock_json/3MINDIA.json
predictrampyfinance/stock_json/3PLAND.json
predictrampyfinance/stock_json/5PAISA.json
predictrampyfinance/stock_json/63MOONS.json
predictrampyfinance/stock_json/AAKASH.json
predictrampyfinance/stock_json/AAREYDRUGS.json
predictrampyfinance/stock_json/AARON.json
predictrampyfinance/stock_json/AARTIDRUGS.json
predictrampyfinance/stock_json/AARTIIND.json
predictrampyfinance/stock_json/AARTISURF.json
predictrampyfinance/stock_json/AARVEEDEN.json
predictrampyfinance/stock_json/AARVI.json
predictrampyfinance/stock_json/AAVAS.json
predictrampyfinance/stock_json/ABB.json
predictrampyfinance/stock_json/ABBOTINDIA.json
predictrampyfinance/stock_json/ABCAPITAL.json
predictrampyfinance/stock_json/ABFRL.json
predictrampyfinance/stock_json/ABMINTLLTD.json
predictrampyfinance/stock_json/ABSLAMC.json
predictrampyfinance/stock_json/ACC.json
predictrampyfinance/stock_json/ACCELYA.json
predictrampyfinance/stock_json/ACCURACY.json
predictrampyfinance/stock_json/ACE.json
predictrampyfinance/stock_json/ADANIENT.json
predictrampyfinance/stock_json/ADANIGREEN.json
predictrampyfinance/stock_json/ADANIPORTS.json
predictrampyfinance/stock_json/ADANIPOWER.json
predictrampyfinance/stock_json/ADFFOODS.json
predictrampyfinance/stock_json/ADROITINFO.json
predictrampyfinance/stock_json/ADSL.json
predictrampyfinance/stock_json/ADVANIHOTR.json
predictrampyfinance/stock_json/ADVENZYMES.json
predictrampyfinance/stock_json/AFFLE.json
predictrampyfinance/stock_json/AGARIND.json
predictrampyfinance/stock_json/AGROPHOS.json
predictrampyfinance/stock_json/AHLADA.json
predictrampyfinance/stock_json/AHLEAST.json
predictrampyfinance/stock_json/AHLUCONT.json
predictrampyfinance/stock_json/AIAENG.json
predictrampyfinance/stock_json/AIRAN.json
predictrampyfinance-0.1.8.dist-info/METADATA
predictrampyfinance-0.1.8.dist-info/WHEEL
predictrampyfinance-0.1.8.dist-info/top_level.txt
predictrampyfinance-0.1.8.dist-info/RECORD
