Metadata-Version: 2.4
Name: predictrampyfinance
Version: 0.1.8
Summary: Access prepackaged stock-level financial data (JSON) via a simple Python API.
Home-page: https://pypi.org/project/predictrampyfinance
Author: PredictRAM Data
Author-email: support@predictram.com
Classifier: Programming Language :: Python :: 3
Classifier: License :: OSI Approved :: MIT License
Dynamic: author
Dynamic: author-email
Dynamic: classifier
Dynamic: description
Dynamic: description-content-type
Dynamic: home-page
Dynamic: summary
